ezai_util/__init__.py
ezai_util/configs.py
ezai_util/dict.py
ezai_util/fmt.py
ezai_util/fs.py
ezai_util/json.py
ezai_util/res.py
ezai_util/version.txt
ezai_util/env/__init__.py
ezai_util/env/env_util.py
ezai_util/image/__init__.py
ezai_util/image/cv2_util.py
ezai_util/image/np_util.py
ezai_util/image/rw.py
ezai_util-0.0.4.dist-info/METADATA
ezai_util-0.0.4.dist-info/WHEEL
ezai_util-0.0.4.dist-info/entry_points.txt
ezai_util-0.0.4.dist-info/top_level.txt
ezai_util-0.0.4.dist-info/RECORD
